luann/.VSCodeCounter/2025-03-07_17-33-41/details.md
luann/.VSCodeCounter/2025-03-07_17-33-41/diff-details.md
luann/.VSCodeCounter/2025-03-07_17-33-41/diff.csv
luann/.VSCodeCounter/2025-03-07_17-33-41/diff.md
luann/.VSCodeCounter/2025-03-07_17-33-41/diff.txt
luann/.VSCodeCounter/2025-03-07_17-33-41/results.csv
luann/.VSCodeCounter/2025-03-07_17-33-41/results.json
luann/.VSCodeCounter/2025-03-07_17-33-41/results.md
luann/.VSCodeCounter/2025-03-07_17-33-41/results.txt
luann/__init__.py
luann/__main__.py
luann/agent.py
luann/cli/cli.py
luann/client/__init__.py
luann/client/client.py
luann/client/streaming.py
luann/config.py
luann/constants.py
luann/data_sources/connectors.py
luann/data_sources/connectors_helper.py
luann/embeddings.py
luann/errors.py
luann/functions/__init__.py
luann/functions/function_sets/ast_parsers.py
luann/functions/function_sets/base.py
luann/functions/function_sets/multi_agent.py
luann/functions/functions.py
luann/functions/helpers.py
luann/functions/schema_generator.py
luann/humans/__init__.py
luann/humans/default_humans/Chad_basic.txt
luann/humans/examples/basic.txt
luann/interface.py
luann/llm_api/__init__.py
luann/llm_api/anthropic.py
luann/llm_api/azure_openai.py
luann/llm_api/azure_openai_constants.py
luann/llm_api/google_ai.py
luann/llm_api/helpers.py
luann/llm_api/llm_api_tools.py
luann/llm_api/openai.py
luann/local_llm/__init__.py
luann/local_llm/chat_completion_proxy.py
luann/local_llm/constants.py
luann/local_llm/function_parser.py
luann/local_llm/grammars/__init__.py
luann/local_llm/grammars/gbnf_grammar_generator.py
luann/local_llm/grammars/json.gbnf
luann/local_llm/grammars/json_func_calls_with_inner_thoughts.gbnf
luann/local_llm/json_parser.py
luann/local_llm/llm_chat_completion_wrappers/__init__.py
luann/local_llm/llm_chat_completion_wrappers/airoboros.py
luann/local_llm/llm_chat_completion_wrappers/chatml.py
luann/local_llm/llm_chat_completion_wrappers/configurable_wrapper.py
luann-0.2.1.dist-info/entry_points.txt
luann-0.2.1.dist-info/METADATA
luann-0.2.1.dist-info/WHEEL
luann-0.2.1.dist-info/RECORD
