Metadata-Version: 2.3
Name: luann
Version: 0.2.1
Summary: to better use of llm
License: Apache License
Author: Luann Team
Requires-Python: >=3.10,<4.0
Classifier: License :: Other/Proprietary License
Classifier: Programming Language :: Python :: 3
Classifier: Programming Language :: Python :: 3.10
Classifier: Programming Language :: Python :: 3.11
Classifier: Programming Language :: Python :: 3.12
Classifier: Programming Language :: Python :: 3.13
Requires-Dist: alembic (>=1.15.1,<2.0.0)
Requires-Dist: anthropic (>=0.49.0,<0.50.0)
Requires-Dist: demjson3 (>=3.0.6,<4.0.0)
Requires-Dist: docstring-parser (>=0.16,<0.17)
Requires-Dist: e2b-code-interpreter (==1.0.3)
Requires-Dist: fastapi (>=0.115.11,<0.116.0)
Requires-Dist: httpx-sse (>=0.4.0,<0.5.0)
Requires-Dist: jinja2 (>=3.1.6,<4.0.0)
Requires-Dist: llama-index (==0.12.2)
Requires-Dist: numpy (==1.26.2)
Requires-Dist: openai (==1.60.0)
Requires-Dist: pathvalidate (>=3.2.3,<4.0.0)
Requires-Dist: pgvector (>=0.3.6,<0.4.0)
Requires-Dist: prettytable (>=3.15.1,<4.0.0)
Requires-Dist: psycopg2 (>=2.9.10,<3.0.0)
Requires-Dist: pydantic-settings (>=2.8.1,<3.0.0)
Requires-Dist: python-multipart (>=0.0.20,<0.0.21)
Requires-Dist: pytz (>=2025.1,<2026.0)
Requires-Dist: pyyaml (>=6.0.2,<7.0.0)
Requires-Dist: questionary (==2.0.1)
Requires-Dist: rich (>=13.9.4,<14.0.0)
Requires-Dist: sqlalchemy (==2.0.25)
Requires-Dist: tiktoken (>=0.9.0,<0.10.0)
Requires-Dist: typer (==0.9.0)
Requires-Dist: uvicorn (>=0.34.0,<0.35.0)
